jiracards
