Metadata-Version: 1.0
Name: jira-cards
Version: 0.2.0
Summary: JiraCards prints agile cards for your physical board from Jira. The issues are read from a Jira Agile Board or individual issues can be provided to create single cards.
Home-page: https://github.com/hypebeast/jiraCards
Author: Sebastian Ruml
Author-email: sebastian@sebastianruml.com
License: The MIT License (MIT)
